[{"name": "benchmarks.NestedFrameAddNested.peakmem_run", "idx": null, "pretty_name": "benchmarks.NestedFrameAddNested.peakmem_run", "last_rev": 177, "last_value": 148492288.0, "last_err": 4823625.142857143, "prev_value": null, "change_rev": null}, {"name": "benchmarks.NestedFrameAddNested.time_run", "idx": null, "pretty_name": "benchmarks.NestedFrameAddNested.time_run", "last_rev": 177, "last_value": 0.23827697650000346, "last_err": 0.01747080267716155, "prev_value": null, "change_rev": null}, {"name": "benchmarks.NestedFrameQuery.peakmem_run", "idx": null, "pretty_name": "benchmarks.NestedFrameQuery.peakmem_run", "last_rev": 177, "last_value": 149413888.0, "last_err": 4526275.047619048, "prev_value": null, "change_rev": null}, {"name": "benchmarks.NestedFrameQuery.time_run", "idx": null, "pretty_name": "benchmarks.NestedFrameQuery.time_run", "last_rev": 177, "last_value": 0.4907983345000275, "last_err": 0.08466626657162497, "prev_value": null, "change_rev": null}, {"name": "benchmarks.NestedFrameReduce.peakmem_run", "idx": null, "pretty_name": "benchmarks.NestedFrameReduce.peakmem_run", "last_rev": 177, "last_value": 135352320.0, "last_err": 791210.6666666666, "prev_value": 148064256.0, "change_rev": [139, 141]}, {"name": "benchmarks.NestedFrameReduce.time_run", "idx": null, "pretty_name": "benchmarks.NestedFrameReduce.time_run", "last_rev": 177, "last_value": 0.2442806280000127, "last_err": 0.025833365338453523, "prev_value": 0.3813299149999949, "change_rev": [63, 68]}]